data_spec_validator/__init__.py
data_spec_validator/__version__.py
data_spec_validator/decorator/__init__.py
data_spec_validator/decorator/decorators.py
data_spec_validator/spec/__init__.py
data_spec_validator/spec/actions.py
data_spec_validator/spec/checks.py
data_spec_validator/spec/defines.py
data_spec_validator/spec/features.py
data_spec_validator/spec/utils.py
data_spec_validator/spec/validators.py
data_spec_validator/spec/wrappers.py
data_spec_validator/spec/custom_spec/__init__.py
data_spec_validator/spec/custom_spec/defines.py
test/__init__.py
test/test_class_type_spec.py
test/test_decorator_dj.py
test/test_decorator_drf.py
test/test_nested_spec.py
test/test_spec.py
test/utils.py
data_spec_validator-3.4.1.dist-info/LICENSE
data_spec_validator-3.4.1.dist-info/METADATA
data_spec_validator-3.4.1.dist-info/WHEEL
data_spec_validator-3.4.1.dist-info/top_level.txt
data_spec_validator-3.4.1.dist-info/RECORD
