Metadata-Version: 2.1
Name: data-spec-validator
Version: 3.4.1
Summary: Validation tool for API/Function parameters
Home-page: https://github.com/hardcoretech/data-spec-validator
Author: GoFreight
Author-email: pypi@hardcoretech.co
Project-URL: Changelog, https://github.com/hardcoretech/data-spec-validator/blob/develop/CHANGELOG.md
Classifier: Programming Language :: Python :: 3
Classifier: Framework :: Django :: 3
Classifier: Framework :: Django :: 4
Classifier: License :: OSI Approved :: MIT License
Classifier: Operating System :: OS Independent
Requires-Python: >=3.8
License-File: LICENSE
Requires-Dist: python-dateutil
Provides-Extra: decorator
Requires-Dist: Django >=3.0 ; extra == 'decorator'
Requires-Dist: djangorestframework ; extra == 'decorator'
Provides-Extra: decorator-dj
Requires-Dist: Django >=3.0 ; extra == 'decorator-dj'
